public/verilog/verilog_code.v
module mini_mac (
    input clk,
    input [3:0] a,
    input [3:0] b,
    output [7:0] out
);
    reg [7:0] out_temp;
    always @(posedge clk) out_temp <= a * b;
    assign out = out_temp;
endmodule

public/verilog/verilog_code_tb.v
`timescale 1ns/1ps
module mini_mac_tb;
    reg [8:0] test_bits;
    integer i;  // 移出迴圈外，修正標準 Verilog 相容性

    // 解析與宣告接線
    wire  clk = test_bits[0];
    wire [3:0] a = test_bits[4:1];
    wire [3:0] b = test_bits[8:5];
    wire  out;

    mini_mac uut (
        .clk(clk),
        .a(a),
        .b(b),
        .out(out)
    );

    initial begin
        $dumpfile("output.vcd");
        $dumpvars(0, mini_mac_tb);
        for (i = 0; i < 512; i = i + 1) begin
            test_bits = i;
            #10;
        end
        $finish;
    end
endmodule

public/verilog/output.vcd
$date
	Sat Apr 11 13:34:09 2026
$end
$version
	Icarus Verilog
$end
$timescale
	1ps
$end
$scope module mini_mac_tb $end
$var wire 1 ! out $end
$var wire 1 " clk $end
$var wire 4 # b [3:0] $end
$var wire 4 $ a [3:0] $end
$var reg 9 % test_bits [8:0] $end
$var integer 32 & i [31:0] $end
$scope module uut $end
$var wire 4 ' a [3:0] $end
$var wire 4 ( b [3:0] $end
$var wire 1 " clk $end
$var wire 8 ) out [7:0] $end
$var reg 8 * out_temp [7:0] $end
$upscope $end
$upscope $end
$enddefinitions $end
$comment Show the parameter values. $end
$dumpall
$end
#0
$dumpvars
bx *
bx )
b0 (
b0 '
b0 &
b0 %
b0 $
b0 #
0"
x!
$end
#10000
0!
b0 )
b0 *
1"
b1 %
b1 &
#20000
0"
b1 $
b1 '
b10 %
b10 &
#30000
1"
b11 %
b11 &
#40000
0"
b10 $
b10 '
b100 %
b100 &
#50000
1"
b101 %
b101 &
#60000
0"
b11 $
b11 '
b110 %
b110 &
#70000
1"
b111 %
b111 &
#80000
0"
b100 $
b100 '
b1000 %
b1000 &
#90000
1"
b1001 %
b1001 &
#100000
0"
b101 $
b101 '
b1010 %
b1010 &
#110000
1"
b1011 %
b1011 &
#120000
0"
b110 $
b110 '
b1100 %
b1100 &
#130000
1"
b1101 %
b1101 &
#140000
0"
b111 $
b111 '
b1110 %
b1110 &
#150000
1"
b1111 %
b1111 &
#160000
0"
b1000 $
b1000 '
b10000 %
b10000 &
#170000
1"
b10001 %
b10001 &
#180000
0"
b1001 $
b1001 '
b10010 %
b10010 &
#190000
1"
b10011 %
b10011 &
#200000
0"
b1010 $
b1010 '
b10100 %
b10100 &
#210000
1"
b10101 %
b10101 &
#220000
0"
b1011 $
b1011 '
b10110 %
b10110 &
#230000
1"
b10111 %
b10111 &
#240000
0"
b1100 $
b1100 '
b11000 %
b11000 &
#250000
1"
b11001 %
b11001 &
#260000
0"
b1101 $
b1101 '
b11010 %
b11010 &
#270000
1"
b11011 %
b11011 &
#280000
0"
b1110 $
b1110 '
b11100 %
b11100 &
#290000
1"
b11101 %
b11101 &
#300000
0"
b1111 $
b1111 '
b11110 %
b11110 &
#310000
1"
b11111 %
b11111 &
#320000
0"
b0 $
b0 '
b1 #
b1 (
b100000 %
b100000 &
#330000
1"
b100001 %
b100001 &
#340000
0"
b1 $
b1 '
b100010 %
b100010 &
#350000
1!
b1 )
b1 *
1"
b100011 %
b100011 &
#360000
0"
b10 $
b10 '
b100100 %
b100100 &
#370000
0!
b10 )
b10 *
1"
b100101 %
b100101 &
#380000
0"
b11 $
b11 '
b100110 %
b100110 &
#390000
1!
b11 )
b11 *
1"
b100111 %
b100111 &
#400000
0"
b100 $
b100 '
b101000 %
b101000 &
#410000
0!
b100 )
b100 *
1"
b101001 %
b101001 &
#420000
0"
b101 $
b101 '
b101010 %
b101010 &
#430000
1!
b101 )
b101 *
1"
b101011 %
b101011 &
#440000
0"
b110 $
b110 '
b101100 %
b101100 &
#450000
0!
b110 )
b110 *
1"
b101101 %
b101101 &
#460000
0"
b111 $
b111 '
b101110 %
b101110 &
#470000
1!
b111 )
b111 *
1"
b101111 %
b101111 &
#480000
0"
b1000 $
b1000 '
b110000 %
b110000 &
#490000
0!
b1000 )
b1000 *
1"
b110001 %
b110001 &
#500000
0"
b1001 $
b1001 '
b110010 %
b110010 &
#510000
1!
b1001 )
b1001 *
1"
b110011 %
b110011 &
#520000
0"
b1010 $
b1010 '
b110100 %
b110100 &
#530000
0!
b1010 )
b1010 *
1"
b110101 %
b110101 &
#540000
0"
b1011 $
b1011 '
b110110 %
b110110 &
#550000
1!
b1011 )
b1011 *
1"
b110111 %
b110111 &
#560000
0"
b1100 $
b1100 '
b111000 %
b111000 &
#570000
0!
b1100 )
b1100 *
1"
b111001 %
b111001 &
#580000
0"
b1101 $
b1101 '
b111010 %
b111010 &
#590000
1!
b1101 )
b1101 *
1"
b111011 %
b111011 &
#600000
0"
b1110 $
b1110 '
b111100 %
b111100 &
#610000
0!
b1110 )
b1110 *
1"
b111101 %
b111101 &
#620000
0"
b1111 $
b1111 '
b111110 %
b111110 &
#630000
1!
b1111 )
b1111 *
1"
b111111 %
b111111 &
#640000
0"
b0 $
b0 '
b10 #
b10 (
b1000000 %
b1000000 &
#650000
0!
b0 )
b0 *
1"
b1000001 %
b1000001 &
#660000
0"
b1 $
b1 '
b1000010 %
b1000010 &
#670000
b10 )
b10 *
1"
b1000011 %
b1000011 &
#680000
0"
b10 $
b10 '
b1000100 %
b1000100 &
#690000
b100 )
b100 *
1"
b1000101 %
b1000101 &
#700000
0"
b11 $
b11 '
b1000110 %
b1000110 &
#710000
b110 )
b110 *
1"
b1000111 %
b1000111 &
#720000
0"
b100 $
b100 '
b1001000 %
b1001000 &
#730000
b1000 )
b1000 *
1"
b1001001 %
b1001001 &
#740000
0"
b101 $
b101 '
b1001010 %
b1001010 &
#750000
b1010 )
b1010 *
1"
b1001011 %
b1001011 &
#760000
0"
b110 $
b110 '
b1001100 %
b1001100 &
#770000
b1100 )
b1100 *
1"
b1001101 %
b1001101 &
#780000
0"
b111 $
b111 '
b1001110 %
b1001110 &
#790000
b1110 )
b1110 *
1"
b1001111 %
b1001111 &
#800000
0"
b1000 $
b1000 '
b1010000 %
b1010000 &
#810000
b10000 )
b10000 *
1"
b1010001 %
b1010001 &
#820000
0"
b1001 $
b1001 '
b1010010 %
b1010010 &
#830000
b10010 )
b10010 *
1"
b1010011 %
b1010011 &
#840000
0"
b1010 $
b1010 '
b1010100 %
b1010100 &
#850000
b10100 )
b10100 *
1"
b1010101 %
b1010101 &
#860000
0"
b1011 $
b1011 '
b1010110 %
b1010110 &
#870000
b10110 )
b10110 *
1"
b1010111 %
b1010111 &
#880000
0"
b1100 $
b1100 '
b1011000 %
b1011000 &
#890000
b11000 )
b11000 *
1"
b1011001 %
b1011001 &
#900000
0"
b1101 $
b1101 '
b1011010 %
b1011010 &
#910000
b11010 )
b11010 *
1"
b1011011 %
b1011011 &
#920000
0"
b1110 $
b1110 '
b1011100 %
b1011100 &
#930000
b11100 )
b11100 *
1"
b1011101 %
b1011101 &
#940000
0"
b1111 $
b1111 '
b1011110 %
b1011110 &
#950000
b11110 )
b11110 *
1"
b1011111 %
b1011111 &
#960000
0"
b0 $
b0 '
b11 #
b11 (
b1100000 %
b1100000 &
#970000
b0 )
b0 *
1"
b1100001 %
b1100001 &
#980000
0"
b1 $
b1 '
b1100010 %
b1100010 &
#990000
1!
b11 )
b11 *
1"
b1100011 %
b1100011 &
#1000000
0"
b10 $
b10 '
b1100100 %
b1100100 &
#1010000
0!
b110 )
b110 *
1"
b1100101 %
b1100101 &
#1020000
0"
b11 $
b11 '
b1100110 %
b1100110 &
#1030000
1!
b1001 )
b1001 *
1"
b1100111 %
b1100111 &
#1040000
0"
b100 $
b100 '
b1101000 %
b1101000 &
#1050000
0!
b1100 )
b1100 *
1"
b1101001 %
b1101001 &
#1060000
0"
b101 $
b101 '
b1101010 %
b1101010 &
#1070000
1!
b1111 )
b1111 *
1"
b1101011 %
b1101011 &
#1080000
0"
b110 $
b110 '
b1101100 %
b1101100 &
#1090000
0!
b10010 )
b10010 *
1"
b1101101 %
b1101101 &
#1100000
0"
b111 $
b111 '
b1101110 %
b1101110 &
#1110000
1!
b10101 )
b10101 *
1"
b1101111 %
b1101111 &
#1120000
0"
b1000 $
b1000 '
b1110000 %
b1110000 &
#1130000
0!
b11000 )
b11000 *
1"
b1110001 %
b1110001 &
#1140000
0"
b1001 $
b1001 '
b1110010 %
b1110010 &
#1150000
1!
b11011 )
b11011 *
1"
b1110011 %
b1110011 &
#1160000
0"
b1010 $
b1010 '
b1110100 %
b1110100 &
#1170000
0!
b11110 )
b11110 *
1"
b1110101 %
b1110101 &
#1180000
0"
b1011 $
b1011 '
b1110110 %
b1110110 &
#1190000
1!
b100001 )
b100001 *
1"
b1110111 %
b1110111 &
#1200000
0"
b1100 $
b1100 '
b1111000 %
b1111000 &
#1210000
0!
b100100 )
b100100 *
1"
b1111001 %
b1111001 &
#1220000
0"
b1101 $
b1101 '
b1111010 %
b1111010 &
#1230000
1!
b100111 )
b100111 *
1"
b1111011 %
b1111011 &
#1240000
0"
b1110 $
b1110 '
b1111100 %
b1111100 &
#1250000
0!
b101010 )
b101010 *
1"
b1111101 %
b1111101 &
#1260000
0"
b1111 $
b1111 '
b1111110 %
b1111110 &
#1270000
1!
b101101 )
b101101 *
1"
b1111111 %
b1111111 &
#1280000
0"
b0 $
b0 '
b100 #
b100 (
b10000000 %
b10000000 &
#1290000
0!
b0 )
b0 *
1"
b10000001 %
b10000001 &
#1300000
0"
b1 $
b1 '
b10000010 %
b10000010 &
#1310000
b100 )
b100 *
1"
b10000011 %
b10000011 &
#1320000
0"
b10 $
b10 '
b10000100 %
b10000100 &
#1330000
b1000 )
b1000 *
1"
b10000101 %
b10000101 &
#1340000
0"
b11 $
b11 '
b10000110 %
b10000110 &
#1350000
b1100 )
b1100 *
1"
b10000111 %
b10000111 &
#1360000
0"
b100 $
b100 '
b10001000 %
b10001000 &
#1370000
b10000 )
b10000 *
1"
b10001001 %
b10001001 &
#1380000
0"
b101 $
b101 '
b10001010 %
b10001010 &
#1390000
b10100 )
b10100 *
1"
b10001011 %
b10001011 &
#1400000
0"
b110 $
b110 '
b10001100 %
b10001100 &
#1410000
b11000 )
b11000 *
1"
b10001101 %
b10001101 &
#1420000
0"
b111 $
b111 '
b10001110 %
b10001110 &
#1430000
b11100 )
b11100 *
1"
b10001111 %
b10001111 &
#1440000
0"
b1000 $
b1000 '
b10010000 %
b10010000 &
#1450000
b100000 )
b100000 *
1"
b10010001 %
b10010001 &
#1460000
0"
b1001 $
b1001 '
b10010010 %
b10010010 &
#1470000
b100100 )
b100100 *
1"
b10010011 %
b10010011 &
#1480000
0"
b1010 $
b1010 '
b10010100 %
b10010100 &
#1490000
b101000 )
b101000 *
1"
b10010101 %
b10010101 &
#1500000
0"
b1011 $
b1011 '
b10010110 %
b10010110 &
#1510000
b101100 )
b101100 *
1"
b10010111 %
b10010111 &
#1520000
0"
b1100 $
b1100 '
b10011000 %
b10011000 &
#1530000
b110000 )
b110000 *
1"
b10011001 %
b10011001 &
#1540000
0"
b1101 $
b1101 '
b10011010 %
b10011010 &
#1550000
b110100 )
b110100 *
1"
b10011011 %
b10011011 &
#1560000
0"
b1110 $
b1110 '
b10011100 %
b10011100 &
#1570000
b111000 )
b111000 *
1"
b10011101 %
b10011101 &
#1580000
0"
b1111 $
b1111 '
b10011110 %
b10011110 &
#1590000
b111100 )
b111100 *
1"
b10011111 %
b10011111 &
#1600000
0"
b0 $
b0 '
b101 #
b101 (
b10100000 %
b10100000 &
#1610000
b0 )
b0 *
1"
b10100001 %
b10100001 &
#1620000
0"
b1 $
b1 '
b10100010 %
b10100010 &
#1630000
1!
b101 )
b101 *
1"
b10100011 %
b10100011 &
#1640000
0"
b10 $
b10 '
b10100100 %
b10100100 &
#1650000
0!
b1010 )
b1010 *
1"
b10100101 %
b10100101 &
#1660000
0"
b11 $
b11 '
b10100110 %
b10100110 &
#1670000
1!
b1111 )
b1111 *
1"
b10100111 %
b10100111 &
#1680000
0"
b100 $
b100 '
b10101000 %
b10101000 &
#1690000
0!
b10100 )
b10100 *
1"
b10101001 %
b10101001 &
#1700000
0"
b101 $
b101 '
b10101010 %
b10101010 &
#1710000
1!
b11001 )
b11001 *
1"
b10101011 %
b10101011 &
#1720000
0"
b110 $
b110 '
b10101100 %
b10101100 &
#1730000
0!
b11110 )
b11110 *
1"
b10101101 %
b10101101 &
#1740000
0"
b111 $
b111 '
b10101110 %
b10101110 &
#1750000
1!
b100011 )
b100011 *
1"
b10101111 %
b10101111 &
#1760000
0"
b1000 $
b1000 '
b10110000 %
b10110000 &
#1770000
0!
b101000 )
b101000 *
1"
b10110001 %
b10110001 &
#1780000
0"
b1001 $
b1001 '
b10110010 %
b10110010 &
#1790000
1!
b101101 )
b101101 *
1"
b10110011 %
b10110011 &
#1800000
0"
b1010 $
b1010 '
b10110100 %
b10110100 &
#1810000
0!
b110010 )
b110010 *
1"
b10110101 %
b10110101 &
#1820000
0"
b1011 $
b1011 '
b10110110 %
b10110110 &
#1830000
1!
b110111 )
b110111 *
1"
b10110111 %
b10110111 &
#1840000
0"
b1100 $
b1100 '
b10111000 %
b10111000 &
#1850000
0!
b111100 )
b111100 *
1"
b10111001 %
b10111001 &
#1860000
0"
b1101 $
b1101 '
b10111010 %
b10111010 &
#1870000
1!
b1000001 )
b1000001 *
1"
b10111011 %
b10111011 &
#1880000
0"
b1110 $
b1110 '
b10111100 %
b10111100 &
#1890000
0!
b1000110 )
b1000110 *
1"
b10111101 %
b10111101 &
#1900000
0"
b1111 $
b1111 '
b10111110 %
b10111110 &
#1910000
1!
b1001011 )
b1001011 *
1"
b10111111 %
b10111111 &
#1920000
0"
b0 $
b0 '
b110 #
b110 (
b11000000 %
b11000000 &
#1930000
0!
b0 )
b0 *
1"
b11000001 %
b11000001 &
#1940000
0"
b1 $
b1 '
b11000010 %
b11000010 &
#1950000
b110 )
b110 *
1"
b11000011 %
b11000011 &
#1960000
0"
b10 $
b10 '
b11000100 %
b11000100 &
#1970000
b1100 )
b1100 *
1"
b11000101 %
b11000101 &
#1980000
0"
b11 $
b11 '
b11000110 %
b11000110 &
#1990000
b10010 )
b10010 *
1"
b11000111 %
b11000111 &
#2000000
0"
b100 $
b100 '
b11001000 %
b11001000 &
#2010000
b11000 )
b11000 *
1"
b11001001 %
b11001001 &
#2020000
0"
b101 $
b101 '
b11001010 %
b11001010 &
#2030000
b11110 )
b11110 *
1"
b11001011 %
b11001011 &
#2040000
0"
b110 $
b110 '
b11001100 %
b11001100 &
#2050000
b100100 )
b100100 *
1"
b11001101 %
b11001101 &
#2060000
0"
b111 $
b111 '
b11001110 %
b11001110 &
#2070000
b101010 )
b101010 *
1"
b11001111 %
b11001111 &
#2080000
0"
b1000 $
b1000 '
b11010000 %
b11010000 &
#2090000
b110000 )
b110000 *
1"
b11010001 %
b11010001 &
#2100000
0"
b1001 $
b1001 '
b11010010 %
b11010010 &
#2110000
b110110 )
b110110 *
1"
b11010011 %
b11010011 &
#2120000
0"
b1010 $
b1010 '
b11010100 %
b11010100 &
#2130000
b111100 )
b111100 *
1"
b11010101 %
b11010101 &
#2140000
0"
b1011 $
b1011 '
b11010110 %
b11010110 &
#2150000
b1000010 )
b1000010 *
1"
b11010111 %
b11010111 &
#2160000
0"
b1100 $
b1100 '
b11011000 %
b11011000 &
#2170000
b1001000 )
b1001000 *
1"
b11011001 %
b11011001 &
#2180000
0"
b1101 $
b1101 '
b11011010 %
b11011010 &
#2190000
b1001110 )
b1001110 *
1"
b11011011 %
b11011011 &
#2200000
0"
b1110 $
b1110 '
b11011100 %
b11011100 &
#2210000
b1010100 )
b1010100 *
1"
b11011101 %
b11011101 &
#2220000
0"
b1111 $
b1111 '
b11011110 %
b11011110 &
#2230000
b1011010 )
b1011010 *
1"
b11011111 %
b11011111 &
#2240000
0"
b0 $
b0 '
b111 #
b111 (
b11100000 %
b11100000 &
#2250000
b0 )
b0 *
1"
b11100001 %
b11100001 &
#2260000
0"
b1 $
b1 '
b11100010 %
b11100010 &
#2270000
1!
b111 )
b111 *
1"
b11100011 %
b11100011 &
#2280000
0"
b10 $
b10 '
b11100100 %
b11100100 &
#2290000
0!
b1110 )
b1110 *
1"
b11100101 %
b11100101 &
#2300000
0"
b11 $
b11 '
b11100110 %
b11100110 &
#2310000
1!
b10101 )
b10101 *
1"
b11100111 %
b11100111 &
#2320000
0"
b100 $
b100 '
b11101000 %
b11101000 &
#2330000
0!
b11100 )
b11100 *
1"
b11101001 %
b11101001 &
#2340000
0"
b101 $
b101 '
b11101010 %
b11101010 &
#2350000
1!
b100011 )
b100011 *
1"
b11101011 %
b11101011 &
#2360000
0"
b110 $
b110 '
b11101100 %
b11101100 &
#2370000
0!
b101010 )
b101010 *
1"
b11101101 %
b11101101 &
#2380000
0"
b111 $
b111 '
b11101110 %
b11101110 &
#2390000
1!
b110001 )
b110001 *
1"
b11101111 %
b11101111 &
#2400000
0"
b1000 $
b1000 '
b11110000 %
b11110000 &
#2410000
0!
b111000 )
b111000 *
1"
b11110001 %
b11110001 &
#2420000
0"
b1001 $
b1001 '
b11110010 %
b11110010 &
#2430000
1!
b111111 )
b111111 *
1"
b11110011 %
b11110011 &
#2440000
0"
b1010 $
b1010 '
b11110100 %
b11110100 &
#2450000
0!
b1000110 )
b1000110 *
1"
b11110101 %
b11110101 &
#2460000
0"
b1011 $
b1011 '
b11110110 %
b11110110 &
#2470000
1!
b1001101 )
b1001101 *
1"
b11110111 %
b11110111 &
#2480000
0"
b1100 $
b1100 '
b11111000 %
b11111000 &
#2490000
0!
b1010100 )
b1010100 *
1"
b11111001 %
b11111001 &
#2500000
0"
b1101 $
b1101 '
b11111010 %
b11111010 &
#2510000
1!
b1011011 )
b1011011 *
1"
b11111011 %
b11111011 &
#2520000
0"
b1110 $
b1110 '
b11111100 %
b11111100 &
#2530000
0!
b1100010 )
b1100010 *
1"
b11111101 %
b11111101 &
#2540000
0"
b1111 $
b1111 '
b11111110 %
b11111110 &
#2550000
1!
b1101001 )
b1101001 *
1"
b11111111 %
b11111111 &
#2560000
0"
b0 $
b0 '
b1000 #
b1000 (
b100000000 %
b100000000 &
#2570000
0!
b0 )
b0 *
1"
b100000001 %
b100000001 &
#2580000
0"
b1 $
b1 '
b100000010 %
b100000010 &
#2590000
b1000 )
b1000 *
1"
b100000011 %
b100000011 &
#2600000
0"
b10 $
b10 '
b100000100 %
b100000100 &
#2610000
b10000 )
b10000 *
1"
b100000101 %
b100000101 &
#2620000
0"
b11 $
b11 '
b100000110 %
b100000110 &
#2630000
b11000 )
b11000 *
1"
b100000111 %
b100000111 &
#2640000
0"
b100 $
b100 '
b100001000 %
b100001000 &
#2650000
b100000 )
b100000 *
1"
b100001001 %
b100001001 &
#2660000
0"
b101 $
b101 '
b100001010 %
b100001010 &
#2670000
b101000 )
b101000 *
1"
b100001011 %
b100001011 &
#2680000
0"
b110 $
b110 '
b100001100 %
b100001100 &
#2690000
b110000 )
b110000 *
1"
b100001101 %
b100001101 &
#2700000
0"
b111 $
b111 '
b100001110 %
b100001110 &
#2710000
b111000 )
b111000 *
1"
b100001111 %
b100001111 &
#2720000
0"
b1000 $
b1000 '
b100010000 %
b100010000 &
#2730000
b1000000 )
b1000000 *
1"
b100010001 %
b100010001 &
#2740000
0"
b1001 $
b1001 '
b100010010 %
b100010010 &
#2750000
b1001000 )
b1001000 *
1"
b100010011 %
b100010011 &
#2760000
0"
b1010 $
b1010 '
b100010100 %
b100010100 &
#2770000
b1010000 )
b1010000 *
1"
b100010101 %
b100010101 &
#2780000
0"
b1011 $
b1011 '
b100010110 %
b100010110 &
#2790000
b1011000 )
b1011000 *
1"
b100010111 %
b100010111 &
#2800000
0"
b1100 $
b1100 '
b100011000 %
b100011000 &
#2810000
b1100000 )
b1100000 *
1"
b100011001 %
b100011001 &
#2820000
0"
b1101 $
b1101 '
b100011010 %
b100011010 &
#2830000
b1101000 )
b1101000 *
1"
b100011011 %
b100011011 &
#2840000
0"
b1110 $
b1110 '
b100011100 %
b100011100 &
#2850000
b1110000 )
b1110000 *
1"
b100011101 %
b100011101 &
#2860000
0"
b1111 $
b1111 '
b100011110 %
b100011110 &
#2870000
b1111000 )
b1111000 *
1"
b100011111 %
b100011111 &
#2880000
0"
b0 $
b0 '
b1001 #
b1001 (
b100100000 %
b100100000 &
#2890000
b0 )
b0 *
1"
b100100001 %
b100100001 &
#2900000
0"
b1 $
b1 '
b100100010 %
b100100010 &
#2910000
1!
b1001 )
b1001 *
1"
b100100011 %
b100100011 &
#2920000
0"
b10 $
b10 '
b100100100 %
b100100100 &
#2930000
0!
b10010 )
b10010 *
1"
b100100101 %
b100100101 &
#2940000
0"
b11 $
b11 '
b100100110 %
b100100110 &
#2950000
1!
b11011 )
b11011 *
1"
b100100111 %
b100100111 &
#2960000
0"
b100 $
b100 '
b100101000 %
b100101000 &
#2970000
0!
b100100 )
b100100 *
1"
b100101001 %
b100101001 &
#2980000
0"
b101 $
b101 '
b100101010 %
b100101010 &
#2990000
1!
b101101 )
b101101 *
1"
b100101011 %
b100101011 &
#3000000
0"
b110 $
b110 '
b100101100 %
b100101100 &
#3010000
0!
b110110 )
b110110 *
1"
b100101101 %
b100101101 &
#3020000
0"
b111 $
b111 '
b100101110 %
b100101110 &
#3030000
1!
b111111 )
b111111 *
1"
b100101111 %
b100101111 &
#3040000
0"
b1000 $
b1000 '
b100110000 %
b100110000 &
#3050000
0!
b1001000 )
b1001000 *
1"
b100110001 %
b100110001 &
#3060000
0"
b1001 $
b1001 '
b100110010 %
b100110010 &
#3070000
1!
b1010001 )
b1010001 *
1"
b100110011 %
b100110011 &
#3080000
0"
b1010 $
b1010 '
b100110100 %
b100110100 &
#3090000
0!
b1011010 )
b1011010 *
1"
b100110101 %
b100110101 &
#3100000
0"
b1011 $
b1011 '
b100110110 %
b100110110 &
#3110000
1!
b1100011 )
b1100011 *
1"
b100110111 %
b100110111 &
#3120000
0"
b1100 $
b1100 '
b100111000 %
b100111000 &
#3130000
0!
b1101100 )
b1101100 *
1"
b100111001 %
b100111001 &
#3140000
0"
b1101 $
b1101 '
b100111010 %
b100111010 &
#3150000
1!
b1110101 )
b1110101 *
1"
b100111011 %
b100111011 &
#3160000
0"
b1110 $
b1110 '
b100111100 %
b100111100 &
#3170000
0!
b1111110 )
b1111110 *
1"
b100111101 %
b100111101 &
#3180000
0"
b1111 $
b1111 '
b100111110 %
b100111110 &
#3190000
1!
b10000111 )
b10000111 *
1"
b100111111 %
b100111111 &
#3200000
0"
b0 $
b0 '
b1010 #
b1010 (
b101000000 %
b101000000 &
#3210000
0!
b0 )
b0 *
1"
b101000001 %
b101000001 &
#3220000
0"
b1 $
b1 '
b101000010 %
b101000010 &
#3230000
b1010 )
b1010 *
1"
b101000011 %
b101000011 &
#3240000
0"
b10 $
b10 '
b101000100 %
b101000100 &
#3250000
b10100 )
b10100 *
1"
b101000101 %
b101000101 &
#3260000
0"
b11 $
b11 '
b101000110 %
b101000110 &
#3270000
b11110 )
b11110 *
1"
b101000111 %
b101000111 &
#3280000
0"
b100 $
b100 '
b101001000 %
b101001000 &
#3290000
b101000 )
b101000 *
1"
b101001001 %
b101001001 &
#3300000
0"
b101 $
b101 '
b101001010 %
b101001010 &
#3310000
b110010 )
b110010 *
1"
b101001011 %
b101001011 &
#3320000
0"
b110 $
b110 '
b101001100 %
b101001100 &
#3330000
b111100 )
b111100 *
1"
b101001101 %
b101001101 &
#3340000
0"
b111 $
b111 '
b101001110 %
b101001110 &
#3350000
b1000110 )
b1000110 *
1"
b101001111 %
b101001111 &
#3360000
0"
b1000 $
b1000 '
b101010000 %
b101010000 &
#3370000
b1010000 )
b1010000 *
1"
b101010001 %
b101010001 &
#3380000
0"
b1001 $
b1001 '
b101010010 %
b101010010 &
#3390000
b1011010 )
b1011010 *
1"
b101010011 %
b101010011 &
#3400000
0"
b1010 $
b1010 '
b101010100 %
b101010100 &
#3410000
b1100100 )
b1100100 *
1"
b101010101 %
b101010101 &
#3420000
0"
b1011 $
b1011 '
b101010110 %
b101010110 &
#3430000
b1101110 )
b1101110 *
1"
b101010111 %
b101010111 &
#3440000
0"
b1100 $
b1100 '
b101011000 %
b101011000 &
#3450000
b1111000 )
b1111000 *
1"
b101011001 %
b101011001 &
#3460000
0"
b1101 $
b1101 '
b101011010 %
b101011010 &
#3470000
b10000010 )
b10000010 *
1"
b101011011 %
b101011011 &
#3480000
0"
b1110 $
b1110 '
b101011100 %
b101011100 &
#3490000
b10001100 )
b10001100 *
1"
b101011101 %
b101011101 &
#3500000
0"
b1111 $
b1111 '
b101011110 %
b101011110 &
#3510000
b10010110 )
b10010110 *
1"
b101011111 %
b101011111 &
#3520000
0"
b0 $
b0 '
b1011 #
b1011 (
b101100000 %
b101100000 &
#3530000
b0 )
b0 *
1"
b101100001 %
b101100001 &
#3540000
0"
b1 $
b1 '
b101100010 %
b101100010 &
#3550000
1!
b1011 )
b1011 *
1"
b101100011 %
b101100011 &
#3560000
0"
b10 $
b10 '
b101100100 %
b101100100 &
#3570000
0!
b10110 )
b10110 *
1"
b101100101 %
b101100101 &
#3580000
0"
b11 $
b11 '
b101100110 %
b101100110 &
#3590000
1!
b100001 )
b100001 *
1"
b101100111 %
b101100111 &
#3600000
0"
b100 $
b100 '
b101101000 %
b101101000 &
#3610000
0!
b101100 )
b101100 *
1"
b101101001 %
b101101001 &
#3620000
0"
b101 $
b101 '
b101101010 %
b101101010 &
#3630000
1!
b110111 )
b110111 *
1"
b101101011 %
b101101011 &
#3640000
0"
b110 $
b110 '
b101101100 %
b101101100 &
#3650000
0!
b1000010 )
b1000010 *
1"
b101101101 %
b101101101 &
#3660000
0"
b111 $
b111 '
b101101110 %
b101101110 &
#3670000
1!
b1001101 )
b1001101 *
1"
b101101111 %
b101101111 &
#3680000
0"
b1000 $
b1000 '
b101110000 %
b101110000 &
#3690000
0!
b1011000 )
b1011000 *
1"
b101110001 %
b101110001 &
#3700000
0"
b1001 $
b1001 '
b101110010 %
b101110010 &
#3710000
1!
b1100011 )
b1100011 *
1"
b101110011 %
b101110011 &
#3720000
0"
b1010 $
b1010 '
b101110100 %
b101110100 &
#3730000
0!
b1101110 )
b1101110 *
1"
b101110101 %
b101110101 &
#3740000
0"
b1011 $
b1011 '
b101110110 %
b101110110 &
#3750000
1!
b1111001 )
b1111001 *
1"
b101110111 %
b101110111 &
#3760000
0"
b1100 $
b1100 '
b101111000 %
b101111000 &
#3770000
0!
b10000100 )
b10000100 *
1"
b101111001 %
b101111001 &
#3780000
0"
b1101 $
b1101 '
b101111010 %
b101111010 &
#3790000
1!
b10001111 )
b10001111 *
1"
b101111011 %
b101111011 &
#3800000
0"
b1110 $
b1110 '
b101111100 %
b101111100 &
#3810000
0!
b10011010 )
b10011010 *
1"
b101111101 %
b101111101 &
#3820000
0"
b1111 $
b1111 '
b101111110 %
b101111110 &
#3830000
1!
b10100101 )
b10100101 *
1"
b101111111 %
b101111111 &
#3840000
0"
b0 $
b0 '
b1100 #
b1100 (
b110000000 %
b110000000 &
#3850000
0!
b0 )
b0 *
1"
b110000001 %
b110000001 &
#3860000
0"
b1 $
b1 '
b110000010 %
b110000010 &
#3870000
b1100 )
b1100 *
1"
b110000011 %
b110000011 &
#3880000
0"
b10 $
b10 '
b110000100 %
b110000100 &
#3890000
b11000 )
b11000 *
1"
b110000101 %
b110000101 &
#3900000
0"
b11 $
b11 '
b110000110 %
b110000110 &
#3910000
b100100 )
b100100 *
1"
b110000111 %
b110000111 &
#3920000
0"
b100 $
b100 '
b110001000 %
b110001000 &
#3930000
b110000 )
b110000 *
1"
b110001001 %
b110001001 &
#3940000
0"
b101 $
b101 '
b110001010 %
b110001010 &
#3950000
b111100 )
b111100 *
1"
b110001011 %
b110001011 &
#3960000
0"
b110 $
b110 '
b110001100 %
b110001100 &
#3970000
b1001000 )
b1001000 *
1"
b110001101 %
b110001101 &
#3980000
0"
b111 $
b111 '
b110001110 %
b110001110 &
#3990000
b1010100 )
b1010100 *
1"
b110001111 %
b110001111 &
#4000000
0"
b1000 $
b1000 '
b110010000 %
b110010000 &
#4010000
b1100000 )
b1100000 *
1"
b110010001 %
b110010001 &
#4020000
0"
b1001 $
b1001 '
b110010010 %
b110010010 &
#4030000
b1101100 )
b1101100 *
1"
b110010011 %
b110010011 &
#4040000
0"
b1010 $
b1010 '
b110010100 %
b110010100 &
#4050000
b1111000 )
b1111000 *
1"
b110010101 %
b110010101 &
#4060000
0"
b1011 $
b1011 '
b110010110 %
b110010110 &
#4070000
b10000100 )
b10000100 *
1"
b110010111 %
b110010111 &
#4080000
0"
b1100 $
b1100 '
b110011000 %
b110011000 &
#4090000
b10010000 )
b10010000 *
1"
b110011001 %
b110011001 &
#4100000
0"
b1101 $
b1101 '
b110011010 %
b110011010 &
#4110000
b10011100 )
b10011100 *
1"
b110011011 %
b110011011 &
#4120000
0"
b1110 $
b1110 '
b110011100 %
b110011100 &
#4130000
b10101000 )
b10101000 *
1"
b110011101 %
b110011101 &
#4140000
0"
b1111 $
b1111 '
b110011110 %
b110011110 &
#4150000
b10110100 )
b10110100 *
1"
b110011111 %
b110011111 &
#4160000
0"
b0 $
b0 '
b1101 #
b1101 (
b110100000 %
b110100000 &
#4170000
b0 )
b0 *
1"
b110100001 %
b110100001 &
#4180000
0"
b1 $
b1 '
b110100010 %
b110100010 &
#4190000
1!
b1101 )
b1101 *
1"
b110100011 %
b110100011 &
#4200000
0"
b10 $
b10 '
b110100100 %
b110100100 &
#4210000
0!
b11010 )
b11010 *
1"
b110100101 %
b110100101 &
#4220000
0"
b11 $
b11 '
b110100110 %
b110100110 &
