public/verilog/verilog_code.v
module full_adder (
    input a, b, cin,
    output sum, cout
);
    assign sum = a ^ b ^ cin;
    assign cout = (a & b) | (b & cin) | (a & cin);
endmodule

public/verilog/verilog_code_tb.v
`timescale 1ns/1ps
module full_adder_tb;
    reg [2:0] test_bits;
    integer i;  // 移出迴圈外，修正標準 Verilog 相容性

    // 解析與宣告接線
    wire  a = test_bits[0];
    wire  b = test_bits[1];
    wire  cin = test_bits[2];
    wire  sum;
    wire  cout;

    full_adder uut (
        .a(a),
        .b(b),
        .cin(cin),
        .sum(sum),
        .cout(cout)
    );

    initial begin
        $dumpfile("output.vcd");
        $dumpvars(0, full_adder_tb);
        for (i = 0; i < 8; i = i + 1) begin
            test_bits = i;
            #10;
        end
        $finish;
    end
endmodule

public/verilog/output.vcd
$date
	Mon Apr 13 13:04:02 2026
$end
$version
	Icarus Verilog
$end
$timescale
	1ps
$end
$scope module full_adder_tb $end
$var wire 1 ! sum $end
$var wire 1 " cout $end
$var wire 1 # cin $end
$var wire 1 $ b $end
$var wire 1 % a $end
$var reg 3 & test_bits [2:0] $end
$var integer 32 ' i [31:0] $end
$scope module uut $end
$var wire 1 % a $end
$var wire 1 $ b $end
$var wire 1 # cin $end
$var wire 1 " cout $end
$var wire 1 ! sum $end
$upscope $end
$upscope $end
$enddefinitions $end
$comment Show the parameter values. $end
$dumpall
$end
#0
$dumpvars
b0 '
b0 &
0%
0$
0#
0"
0!
$end
#10000
1!
1%
b1 &
b1 '
#20000
0%
1$
b10 &
b10 '
#30000
1"
0!
1%
b11 &
b11 '
#40000
0"
1!
0%
0$
1#
b100 &
b100 '
#50000
0!
1"
1%
b101 &
b101 '
#60000
0%
1$
b110 &
b110 '
#70000
1!
1%
b111 &
b111 '
#80000
b1000 '
